mdit/__init__.py
mdit/container.py
mdit/display.py
mdit/document.py
mdit/element.py
mdit/generate.py
mdit/parse.py
mdit/protocol.py
mdit/render.py
mdit/renderable.py
mdit/template.py
mdit/data/__init__.py
mdit/data/file.py
mdit/data/schema.py
mdit/data/schema/document.yaml
mdit/data/schema/element/badge.yaml
mdit/data/schema_/create-badges.yaml
mdit/data/schema_/html-document.yaml
mdit/data/schema_/badge/dynamic.yaml
mdit/data/schema_/element/badges.yaml
mdit/data/schema_/element/image.yaml
mdit/data/schema_/element/_to_review/coc_covenant.yaml
mdit/data/schema_/element/_to_review/heading.yaml
mdit/data/schema_/element/_to_review/highlights.yaml
mdit/data/schema_/element/_to_review/line.yaml
mdit/data/schema_/element/_to_review/newline.yaml
mdit/data/schema_/element/_to_review/paragraph.yaml
mdit/data/schema_/element/_to_review/paragraph_style.yaml
mdit/data/schema_/element/_to_review/spacer.yaml
mdit/data/schema_/element/badge/params.yaml
mdit/data/schema_/html/attrs.yaml
mdit/data/schema_/html/attr/align.yaml
mdit/data/schema_/html/attr/size.yaml
mdit/data/schema_/pepy/badge-params.yaml
mdit/data/schema_/shields/badge-params.yaml
mdit/data/template/code_of_conduct/contributor_covenant.md
mdit/target/__init__.py
mdit/target/md.py
mdit/target/rich.py
mdit-0.1.0.dist-info/METADATA
mdit-0.1.0.dist-info/WHEEL
mdit-0.1.0.dist-info/top_level.txt
mdit-0.1.0.dist-info/RECORD
