Metadata-Version: 2.2
Name: MDit
Version: 0.1.0
Requires-Python: >=3.10
Requires-Dist: sphinx<9,>=7
Requires-Dist: myst-nb<2,>1
Requires-Dist: pydata-sphinx-theme
Requires-Dist: sphinx-design>=0.6
Requires-Dist: sphinx-togglebutton
Requires-Dist: sphinx-copybutton>=0.5
Requires-Dist: sphinxcontrib-mermaid>=0.9
Requires-Dist: sphinx-tippy==0.4.3
Requires-Dist: markdown-it-py
Requires-Dist: mdit-py-plugins
Requires-Dist: linkify-it-py
Requires-Dist: readme-renderer[md]
Requires-Dist: cmarkgfm>=0.8.0
Requires-Dist: zundler==0.2.2
Requires-Dist: IPython
Requires-Dist: jupyterlab_myst
Requires-Dist: pygments
Requires-Dist: rich>=13.8
Requires-Dist: pydantic>=2.9
Requires-Dist: referencing>=0.35.1
Requires-Dist: PkgData<0.2,>=0.1
Requires-Dist: PySerials<0.2,>=0.1
Requires-Dist: PyBadger<0.2,>=0.1
Requires-Dist: PyColorIT<0.2,>=0.1
Requires-Dist: ProtocolMan<0.2,>=0.1
Requires-Dist: HTMP<0.2,>=0.1
Requires-Dist: JSONSchemata<0.2,>=0.1
